dti_conv/.DS_Store
dti_conv/.idea/.gitignore
dti_conv/.idea/dti_conv.iml
dti_conv/.idea/inspectionProfiles/profiles_settings.xml
dti_conv/.idea/misc.xml
dti_conv/.idea/modules.xml
dti_conv/.idea/workspace.xml
dti_conv/__init__.py
dti_conv/main.py
dti_conv-0.1.3.dist-info/METADATA
dti_conv-0.1.3.dist-info/WHEEL
dti_conv-0.1.3.dist-info/entry_points.txt
dti_conv-0.1.3.dist-info/RECORD
